phanterpwa/__init__.py
phanterpwa/__main__.py
phanterpwa/compiler.py
phanterpwa/configer.py
phanterpwa/helpers.py
phanterpwa/mail.py
phanterpwa/reversexml.py
phanterpwa/server.py
phanterpwa/sms.py
phanterpwa/tools.py
phanterpwa/xmlconstructor.py
phanterpwa/backend/__init__.py
phanterpwa/backend/dataforms.py
phanterpwa/backend/decorators.py
phanterpwa/backend/security.py
phanterpwa/backend/pydal/__init__.py
phanterpwa/backend/pydal/auth.py
phanterpwa/backend/pydal/cas.py
phanterpwa/backend/pydal/credentials.py
phanterpwa/backend/pydal/extra_validations.py
phanterpwa/backend/pydal/gallery.py
phanterpwa/backend/pydal/internal_messages.py
phanterpwa/backend/request_handlers/__init__.py
phanterpwa/backend/request_handlers/admin.py
phanterpwa/backend/request_handlers/auth.py
phanterpwa/backend/request_handlers/cas.py
phanterpwa/backend/request_handlers/credentials.py
phanterpwa/backend/request_handlers/decorators.py
phanterpwa/backend/request_handlers/errors.py
phanterpwa/backend/request_handlers/i18n_server.py
phanterpwa/backend/request_handlers/internal_messages.py
phanterpwa/backend/request_handlers/oauth.py
phanterpwa/backend/request_handlers/websocket.py
phanterpwa/backend/request_handlers/welcome.py
phanterpwa/captchasvg/__init__.py
phanterpwa/captchasvg/captcha.py
phanterpwa/captchasvg/captchadata.json
phanterpwa/captchasvg/recipes/__init__.py
phanterpwa/captchasvg/recipes/circle.recs
phanterpwa/captchasvg/recipes/heart.recs
phanterpwa/captchasvg/recipes/octagon.recs
phanterpwa/captchasvg/recipes/square.recs
phanterpwa/captchasvg/recipes/star.recs
phanterpwa/captchasvg/sass/__init__.py
phanterpwa/captchasvg/sass/captcha.sass
phanterpwa/captchasvg/vectors/__init__.py
phanterpwa/captchasvg/vectors/animal/butterfly.recs
phanterpwa/captchasvg/vectors/animal/crab.recs
phanterpwa/captchasvg/vectors/animal/pig.recs
phanterpwa/captchasvg/vectors/animal/rabbit.recs
phanterpwa/captchasvg/vectors/animal/rooster.recs
phanterpwa/captchasvg/vectors/arrow/down.recs
phanterpwa-14.4.0.dist-info/LICENSE
phanterpwa-14.4.0.dist-info/METADATA
phanterpwa-14.4.0.dist-info/WHEEL
phanterpwa-14.4.0.dist-info/dependency_links.txt
phanterpwa-14.4.0.dist-info/entry_points.txt
phanterpwa-14.4.0.dist-info/top_level.txt
phanterpwa-14.4.0.dist-info/RECORD
