Metadata-Version: 2.1
Name: phanterpwa
Version: 14.4.0
Summary: Tools for the phanterpwadeveloper framework
Home-page: https://github.com/PhanterJR/phanterpwa
Author: PhanterJR
Author-email: phanterjr@conexaodidata.com.br
Maintainer: PhanterJR
Maintainer-email: phanterjr@conexaodidata.com.br
License: MIT
Platform: any
Classifier: Development Status :: 5 - Production/Stable
Classifier: Environment :: Web Environment
Classifier: Intended Audience :: Developers
Classifier: License :: OSI Approved :: MIT License
Classifier: Operating System :: OS Independent
Classifier: Programming Language :: Python :: 3
Classifier: Programming Language :: Python :: 3.4
Classifier: Programming Language :: Python :: 3.5
Classifier: Programming Language :: Python :: 3.6
Classifier: Programming Language :: Python :: 3.7
Classifier: Programming Language :: Python :: Implementation :: CPython
Classifier: Programming Language :: Python :: Implementation :: PyPy
Classifier: Topic :: Internet :: WWW/HTTP :: Dynamic Content
Classifier: Topic :: Software Development :: Libraries :: Python Modules
Classifier: Topic :: Text Processing :: Markup :: HTML
Requires-Python: >=3.9
License-File: LICENSE
Requires-Dist: psutil
Requires-Dist: tornado
Requires-Dist: libsass
Requires-Dist: transcrypt (==3.9.0)
Requires-Dist: pillow
Requires-Dist: itsdangerous (==2.1.2)
Requires-Dist: requests-oauthlib
Requires-Dist: pydal (>=19.04)
Requires-Dist: passlib
Requires-Dist: appdirs (>=1.4.3)
